vivado_report_parser/__init__.py
vivado_report_parser/helpers.py
vivado_report_parser/metadata.py
vivado_report_parser/parse_vivado_report.py
vivado_report_parser/tables.py
vivado_report_parser-0.5.0.dist-info/COPYING
vivado_report_parser-0.5.0.dist-info/METADATA
vivado_report_parser-0.5.0.dist-info/WHEEL
vivado_report_parser-0.5.0.dist-info/entry_points.txt
vivado_report_parser-0.5.0.dist-info/RECORD
